{
    "swagger": "2.0",
    "info": {
        "description": "API Server for Playlist Synchronizer Application",
        "title": "Playlist Synchronizer API",
        "contact": {},
        "version": "1.0"
    },
    "host": "localhost:8080",
    "basePath": "/",
    "paths": {
        "/api/groups": {
            "get": {
                "security": [
                    {
                        "ApiKeyAuth": []
                    }
                ],
                "description": "get all groups",
                "produces": [
                    "application/json"
                ],
                "tags": [
                    "groups"
                ],
                "summary": "Get All Groups",
                "operationId": "get-all-groups",
                "responses": {
                    "200": {
                        "description": "OK",
                        "schema": {
                            "type": "array",
                            "items": {
                                "$ref": "#/definitions/models.Group"
                            }
                        }
                    },
                    "400": {
                        "description": "Bad Request",
                        "schema": {
                            "$ref": "#/definitions/models.ErrorResponse"
                        }
                    },
                    "401": {
                        "description": "Unauthorized",
                        "schema": {
                            "$ref": "#/definitions/models.ErrorResponse"
                        }
                    },
                    "403": {
                        "description": "Forbidden",
                        "schema": {
                            "$ref": "#/definitions/models.ErrorResponse"
                        }
                    },
                    "404": {
                        "description": "Not Found",
                        "schema": {
                            "$ref": "#/definitions/models.ErrorResponse"
                        }
                    },
                    "500": {
                        "description": "Internal Server Error",
                        "schema": {
                            "$ref": "#/definitions/models.ErrorResponse"
                        }
                    },
                    "default": {
                        "description": "",
                        "schema": {
                            "$ref": "#/definitions/models.ErrorResponse"
                        }
                    }
                }
            },
            "post": {
                "security": [
                    {
                        "ApiKeyAuth": []
                    }
                ],
                "description": "create new group",
                "consumes": [
                    "application/json"
                ],
                "produces": [
                    "application/json"
                ],
                "tags": [
                    "groups"
                ],
                "summary": "Create Group",
                "operationId": "create-group",
                "parameters": [
                    {
                        "description": "group and playlist info",
                        "name": "input",
                        "in": "body",
                        "required": true,
                        "schema": {
                            "$ref": "#/definitions/models.UserCreateGroupInput"
                        }
                    }
                ],
                "responses": {
                    "200": {
                        "description": "OK",
                        "schema": {
                            "$ref": "#/definitions/models.CreateResponse"
                        }
                    },
                    "400": {
                        "description": "Bad Request",
                        "schema": {
                            "$ref": "#/definitions/models.ErrorResponse"
                        }
                    },
                    "401": {
                        "description": "Unauthorized",
                        "schema": {
                            "$ref": "#/definitions/models.ErrorResponse"
                        }
                    },
                    "403": {
                        "description": "Forbidden",
                        "schema": {
                            "$ref": "#/definitions/models.ErrorResponse"
                        }
                    },
                    "404": {
                        "description": "Not Found",
                        "schema": {
                            "$ref": "#/definitions/models.ErrorResponse"
                        }
                    },
                    "500": {
                        "description": "Internal Server Error",
                        "schema": {
                            "$ref": "#/definitions/models.ErrorResponse"
                        }
                    },
                    "default": {
                        "description": "",
                        "schema": {
                            "$ref": "#/definitions/models.ErrorResponse"
                        }
                    }
                }
            }
        },
        "/api/groups/{id}": {
            "get": {
                "security": [
                    {
                        "ApiKeyAuth": []
                    }
                ],
                "description": "get group by id",
                "produces": [
                    "application/json"
                ],
                "tags": [
                    "groups"
                ],
                "summary": "Get Group By ID",
                "operationId": "get-group-by-id",
                "parameters": [
                    {
                        "type": "integer",
                        "description": "group id",
                        "name": "id",
                        "in": "path",
                        "required": true
                    }
                ],
                "responses": {
                    "200": {
                        "description": "OK",
                        "schema": {
                            "$ref": "#/definitions/models.AllGroupData"
                        }
                    },
                    "400": {
                        "description": "Bad Request",
                        "schema": {
                            "$ref": "#/definitions/models.ErrorResponse"
                        }
                    },
                    "401": {
                        "description": "Unauthorized",
                        "schema": {
                            "$ref": "#/definitions/models.ErrorResponse"
                        }
                    },
                    "403": {
                        "description": "Forbidden",
                        "schema": {
                            "$ref": "#/definitions/models.ErrorResponse"
                        }
                    },
                    "404": {
                        "description": "Not Found",
                        "schema": {
                            "$ref": "#/definitions/models.ErrorResponse"
                        }
                    },
                    "500": {
                        "description": "Internal Server Error",
                        "schema": {
                            "$ref": "#/definitions/models.ErrorResponse"
                        }
                    },
                    "default": {
                        "description": "",
                        "schema": {
                            "$ref": "#/definitions/models.ErrorResponse"
                        }
                    }
                }
            },
            "put": {
                "security": [
                    {
                        "ApiKeyAuth": []
                    }
                ],
                "description": "update group",
                "consumes": [
                    "application/json"
                ],
                "produces": [
                    "application/json"
                ],
                "tags": [
                    "groups"
                ],
                "summary": "Update Group",
                "operationId": "update-group",
                "parameters": [
                    {
                        "type": "integer",
                        "description": "group id",
                        "name": "id",
                        "in": "path",
                        "required": true
                    },
                    {
                        "description": "group info",
                        "name": "input",
                        "in": "body",
                        "required": true,
                        "schema": {
                            "$ref": "#/definitions/models.UpdateGroupInput"
                        }
                    }
                ],
                "responses": {
                    "200": {
                        "description": "OK",
                        "schema": {
                            "$ref": "#/definitions/models.StatusResponse"
                        }
                    },
                    "400": {
                        "description": "Bad Request",
                        "schema": {
                            "$ref": "#/definitions/models.ErrorResponse"
                        }
                    },
                    "401": {
                        "description": "Unauthorized",
                        "schema": {
                            "$ref": "#/definitions/models.ErrorResponse"
                        }
                    },
                    "403": {
                        "description": "Forbidden",
                        "schema": {
                            "$ref": "#/definitions/models.ErrorResponse"
                        }
                    },
                    "404": {
                        "description": "Not Found",
                        "schema": {
                            "$ref": "#/definitions/models.ErrorResponse"
                        }
                    },
                    "500": {
                        "description": "Internal Server Error",
                        "schema": {
                            "$ref": "#/definitions/models.ErrorResponse"
                        }
                    },
                    "default": {
                        "description": "",
                        "schema": {
                            "$ref": "#/definitions/models.ErrorResponse"
                        }
                    }
                }
            },
            "delete": {
                "security": [
                    {
                        "ApiKeyAuth": []
                    }
                ],
                "description": "delete group",
                "produces": [
                    "application/json"
                ],
                "tags": [
                    "groups"
                ],
                "summary": "Delete Group",
                "operationId": "delete-group",
                "parameters": [
                    {
                        "type": "integer",
                        "description": "group id",
                        "name": "id",
                        "in": "path",
                        "required": true
                    }
                ],
                "responses": {
                    "200": {
                        "description": "OK",
                        "schema": {
                            "$ref": "#/definitions/models.StatusResponse"
                        }
                    },
                    "400": {
                        "description": "Bad Request",
                        "schema": {
                            "$ref": "#/definitions/models.ErrorResponse"
                        }
                    },
                    "401": {
                        "description": "Unauthorized",
                        "schema": {
                            "$ref": "#/definitions/models.ErrorResponse"
                        }
                    },
                    "403": {
                        "description": "Forbidden",
                        "schema": {
                            "$ref": "#/definitions/models.ErrorResponse"
                        }
                    },
                    "404": {
                        "description": "Not Found",
                        "schema": {
                            "$ref": "#/definitions/models.ErrorResponse"
                        }
                    },
                    "500": {
                        "description": "Internal Server Error",
                        "schema": {
                            "$ref": "#/definitions/models.ErrorResponse"
                        }
                    },
                    "default": {
                        "description": "",
                        "schema": {
                            "$ref": "#/definitions/models.ErrorResponse"
                        }
                    }
                }
            }
        },
        "/api/groups/{id}/leave": {
            "post": {
                "security": [
                    {
                        "ApiKeyAuth": []
                    }
                ],
                "description": "leave group",
                "produces": [
                    "application/json"
                ],
                "tags": [
                    "user-groups"
                ],
                "summary": "Leave Group",
                "operationId": "leave-group",
                "parameters": [
                    {
                        "type": "integer",
                        "description": "group id",
                        "name": "id",
                        "in": "path",
                        "required": true
                    }
                ],
                "responses": {
                    "200": {
                        "description": "OK",
                        "schema": {
                            "$ref": "#/definitions/models.StatusResponse"
                        }
                    },
                    "400": {
                        "description": "Bad Request",
                        "schema": {
                            "$ref": "#/definitions/models.ErrorResponse"
                        }
                    },
                    "401": {
                        "description": "Unauthorized",
                        "schema": {
                            "$ref": "#/definitions/models.ErrorResponse"
                        }
                    },
                    "403": {
                        "description": "Forbidden",
                        "schema": {
                            "$ref": "#/definitions/models.ErrorResponse"
                        }
                    },
                    "404": {
                        "description": "Not Found",
                        "schema": {
                            "$ref": "#/definitions/models.ErrorResponse"
                        }
                    },
                    "500": {
                        "description": "Internal Server Error",
                        "schema": {
                            "$ref": "#/definitions/models.ErrorResponse"
                        }
                    },
                    "default": {
                        "description": "",
                        "schema": {
                            "$ref": "#/definitions/models.ErrorResponse"
                        }
                    }
                }
            }
        },
        "/api/groups/{id}/users": {
            "get": {
                "security": [
                    {
                        "ApiKeyAuth": []
                    }
                ],
                "description": "get all users from group",
                "produces": [
                    "application/json"
                ],
                "tags": [
                    "user-groups"
                ],
                "summary": "Get All Users From Group",
                "operationId": "get-all-users-from-group",
                "parameters": [
                    {
                        "type": "integer",
                        "description": "group id",
                        "name": "id",
                        "in": "path",
                        "required": true
                    }
                ],
                "responses": {
                    "200": {
                        "description": "OK",
                        "schema": {
                            "type": "array",
                            "items": {
                                "$ref": "#/definitions/models.UserGroupData"
                            }
                        }
                    },
                    "400": {
                        "description": "Bad Request",
                        "schema": {
                            "$ref": "#/definitions/models.ErrorResponse"
                        }
                    },
                    "401": {
                        "description": "Unauthorized",
                        "schema": {
                            "$ref": "#/definitions/models.ErrorResponse"
                        }
                    },
                    "403": {
                        "description": "Forbidden",
                        "schema": {
                            "$ref": "#/definitions/models.ErrorResponse"
                        }
                    },
                    "404": {
                        "description": "Not Found",
                        "schema": {
                            "$ref": "#/definitions/models.ErrorResponse"
                        }
                    },
                    "500": {
                        "description": "Internal Server Error",
                        "schema": {
                            "$ref": "#/definitions/models.ErrorResponse"
                        }
                    },
                    "default": {
                        "description": "",
                        "schema": {
                            "$ref": "#/definitions/models.ErrorResponse"
                        }
                    }
                }
            },
            "post": {
                "security": [
                    {
                        "ApiKeyAuth": []
                    }
                ],
                "description": "add user to group",
                "produces": [
                    "application/json"
                ],
                "tags": [
                    "user-groups"
                ],
                "summary": "Add User To Group",
                "operationId": "add-user-to-group",
                "parameters": [
                    {
                        "type": "integer",
                        "description": "group id",
                        "name": "id",
                        "in": "path",
                        "required": true
                    }
                ],
                "responses": {
                    "200": {
                        "description": "OK",
                        "schema": {
                            "$ref": "#/definitions/models.CreateResponse"
                        }
                    },
                    "400": {
                        "description": "Bad Request",
                        "schema": {
                            "$ref": "#/definitions/models.ErrorResponse"
                        }
                    },
                    "401": {
                        "description": "Unauthorized",
                        "schema": {
                            "$ref": "#/definitions/models.ErrorResponse"
                        }
                    },
                    "403": {
                        "description": "Forbidden",
                        "schema": {
                            "$ref": "#/definitions/models.ErrorResponse"
                        }
                    },
                    "404": {
                        "description": "Not Found",
                        "schema": {
                            "$ref": "#/definitions/models.ErrorResponse"
                        }
                    },
                    "500": {
                        "description": "Internal Server Error",
                        "schema": {
                            "$ref": "#/definitions/models.ErrorResponse"
                        }
                    },
                    "default": {
                        "description": "",
                        "schema": {
                            "$ref": "#/definitions/models.ErrorResponse"
                        }
                    }
                }
            }
        },
        "/api/groups/{id}/users/{userID}": {
            "get": {
                "security": [
                    {
                        "ApiKeyAuth": []
                    }
                ],
                "description": "get user by id from group",
                "produces": [
                    "application/json"
                ],
                "tags": [
                    "user-groups"
                ],
                "summary": "Get User By ID From Group",
                "operationId": "get-user-by-id-from-group",
                "parameters": [
                    {
                        "type": "integer",
                        "description": "group id",
                        "name": "id",
                        "in": "path",
                        "required": true
                    },
                    {
                        "type": "integer",
                        "description": "user id",
                        "name": "userID",
                        "in": "path",
                        "required": true
                    }
                ],
                "responses": {
                    "200": {
                        "description": "OK",
                        "schema": {
                            "$ref": "#/definitions/models.UserGroupData"
                        }
                    },
                    "400": {
                        "description": "Bad Request",
                        "schema": {
                            "$ref": "#/definitions/models.ErrorResponse"
                        }
                    },
                    "401": {
                        "description": "Unauthorized",
                        "schema": {
                            "$ref": "#/definitions/models.ErrorResponse"
                        }
                    },
                    "403": {
                        "description": "Forbidden",
                        "schema": {
                            "$ref": "#/definitions/models.ErrorResponse"
                        }
                    },
                    "404": {
                        "description": "Not Found",
                        "schema": {
                            "$ref": "#/definitions/models.ErrorResponse"
                        }
                    },
                    "500": {
                        "description": "Internal Server Error",
                        "schema": {
                            "$ref": "#/definitions/models.ErrorResponse"
                        }
                    },
                    "default": {
                        "description": "",
                        "schema": {
                            "$ref": "#/definitions/models.ErrorResponse"
                        }
                    }
                }
            },
            "put": {
                "security": [
                    {
                        "ApiKeyAuth": []
                    }
                ],
                "description": "update user by id from group",
                "consumes": [
                    "application/json"
                ],
                "produces": [
                    "application/json"
                ],
                "tags": [
                    "user-groups"
                ],
                "summary": "Update User By ID From Group",
                "operationId": "update-user-by-id-from-group",
                "parameters": [
                    {
                        "type": "integer",
                        "description": "group id",
                        "name": "id",
                        "in": "path",
                        "required": true
                    },
                    {
                        "type": "integer",
                        "description": "user id",
                        "name": "userID",
                        "in": "path",
                        "required": true
                    },
                    {
                        "description": "new user role",
                        "name": "input",
                        "in": "body",
                        "required": true,
                        "schema": {
                            "$ref": "#/definitions/models.UpdateUserGroupInput"
                        }
                    }
                ],
                "responses": {
                    "200": {
                        "description": "OK",
                        "schema": {
                            "$ref": "#/definitions/models.StatusResponse"
                        }
                    },
                    "400": {
                        "description": "Bad Request",
                        "schema": {
                            "$ref": "#/definitions/models.ErrorResponse"
                        }
                    },
                    "401": {
                        "description": "Unauthorized",
                        "schema": {
                            "$ref": "#/definitions/models.ErrorResponse"
                        }
                    },
                    "403": {
                        "description": "Forbidden",
                        "schema": {
                            "$ref": "#/definitions/models.ErrorResponse"
                        }
                    },
                    "404": {
                        "description": "Not Found",
                        "schema": {
                            "$ref": "#/definitions/models.ErrorResponse"
                        }
                    },
                    "500": {
                        "description": "Internal Server Error",
                        "schema": {
                            "$ref": "#/definitions/models.ErrorResponse"
                        }
                    },
                    "default": {
                        "description": "",
                        "schema": {
                            "$ref": "#/definitions/models.ErrorResponse"
                        }
                    }
                }
            },
            "delete": {
                "security": [
                    {
                        "ApiKeyAuth": []
                    }
                ],
                "description": "delete user by id from group",
                "produces": [
                    "application/json"
                ],
                "tags": [
                    "user-groups"
                ],
                "summary": "Delete User By ID From Group",
                "operationId": "delete-user-by-id-from-group",
                "parameters": [
                    {
                        "type": "integer",
                        "description": "group id",
                        "name": "id",
                        "in": "path",
                        "required": true
                    },
                    {
                        "type": "integer",
                        "description": "user id",
                        "name": "userID",
                        "in": "path",
                        "required": true
                    }
                ],
                "responses": {
                    "200": {
                        "description": "OK",
                        "schema": {
                            "$ref": "#/definitions/models.StatusResponse"
                        }
                    },
                    "400": {
                        "description": "Bad Request",
                        "schema": {
                            "$ref": "#/definitions/models.ErrorResponse"
                        }
                    },
                    "401": {
                        "description": "Unauthorized",
                        "schema": {
                            "$ref": "#/definitions/models.ErrorResponse"
                        }
                    },
                    "403": {
                        "description": "Forbidden",
                        "schema": {
                            "$ref": "#/definitions/models.ErrorResponse"
                        }
                    },
                    "404": {
                        "description": "Not Found",
                        "schema": {
                            "$ref": "#/definitions/models.ErrorResponse"
                        }
                    },
                    "500": {
                        "description": "Internal Server Error",
                        "schema": {
                            "$ref": "#/definitions/models.ErrorResponse"
                        }
                    },
                    "default": {
                        "description": "",
                        "schema": {
                            "$ref": "#/definitions/models.ErrorResponse"
                        }
                    }
                }
            }
        },
        "/api/playlists": {
            "get": {
                "security": [
                    {
                        "ApiKeyAuth": []
                    }
                ],
                "description": "get all playlists",
                "produces": [
                    "application/json"
                ],
                "tags": [
                    "playlists"
                ],
                "summary": "Get All Playlist",
                "operationId": "get-all-playlists",
                "responses": {
                    "200": {
                        "description": "OK",
                        "schema": {
                            "type": "array",
                            "items": {
                                "$ref": "#/definitions/models.PlayList"
                            }
                        }
                    },
                    "400": {
                        "description": "Bad Request",
                        "schema": {
                            "$ref": "#/definitions/models.ErrorResponse"
                        }
                    },
                    "401": {
                        "description": "Unauthorized",
                        "schema": {
                            "$ref": "#/definitions/models.ErrorResponse"
                        }
                    },
                    "403": {
                        "description": "Forbidden",
                        "schema": {
                            "$ref": "#/definitions/models.ErrorResponse"
                        }
                    },
                    "404": {
                        "description": "Not Found",
                        "schema": {
                            "$ref": "#/definitions/models.ErrorResponse"
                        }
                    },
                    "500": {
                        "description": "Internal Server Error",
                        "schema": {
                            "$ref": "#/definitions/models.ErrorResponse"
                        }
                    },
                    "default": {
                        "description": "",
                        "schema": {
                            "$ref": "#/definitions/models.ErrorResponse"
                        }
                    }
                }
            }
        },
        "/api/playlists/{id}": {
            "get": {
                "security": [
                    {
                        "ApiKeyAuth": []
                    }
                ],
                "description": "get playlist by id",
                "produces": [
                    "application/json"
                ],
                "tags": [
                    "playlists"
                ],
                "summary": "Get Playlist By ID",
                "operationId": "get-playlist-by-id",
                "parameters": [
                    {
                        "type": "integer",
                        "description": "playlist id",
                        "name": "id",
                        "in": "path",
                        "required": true
                    }
                ],
                "responses": {
                    "200": {
                        "description": "OK",
                        "schema": {
                            "$ref": "#/definitions/models.PlayList"
                        }
                    },
                    "400": {
                        "description": "Bad Request",
                        "schema": {
                            "$ref": "#/definitions/models.ErrorResponse"
                        }
                    },
                    "401": {
                        "description": "Unauthorized",
                        "schema": {
                            "$ref": "#/definitions/models.ErrorResponse"
                        }
                    },
                    "403": {
                        "description": "Forbidden",
                        "schema": {
                            "$ref": "#/definitions/models.ErrorResponse"
                        }
                    },
                    "404": {
                        "description": "Not Found",
                        "schema": {
                            "$ref": "#/definitions/models.ErrorResponse"
                        }
                    },
                    "500": {
                        "description": "Internal Server Error",
                        "schema": {
                            "$ref": "#/definitions/models.ErrorResponse"
                        }
                    },
                    "default": {
                        "description": "",
                        "schema": {
                            "$ref": "#/definitions/models.ErrorResponse"
                        }
                    }
                }
            },
            "put": {
                "security": [
                    {
                        "ApiKeyAuth": []
                    }
                ],
                "description": "update playlist",
                "consumes": [
                    "application/json"
                ],
                "produces": [
                    "application/json"
                ],
                "tags": [
                    "playlists"
                ],
                "summary": "Update Playlist",
                "operationId": "update-playlist",
                "parameters": [
                    {
                        "type": "integer",
                        "description": "playlist id",
                        "name": "id",
                        "in": "path",
                        "required": true
                    },
                    {
                        "description": "playlist info",
                        "name": "input",
                        "in": "body",
                        "required": true,
                        "schema": {
                            "$ref": "#/definitions/models.UpdatePlayListInput"
                        }
                    }
                ],
                "responses": {
                    "200": {
                        "description": "OK",
                        "schema": {
                            "$ref": "#/definitions/models.StatusResponse"
                        }
                    },
                    "400": {
                        "description": "Bad Request",
                        "schema": {
                            "$ref": "#/definitions/models.ErrorResponse"
                        }
                    },
                    "401": {
                        "description": "Unauthorized",
                        "schema": {
                            "$ref": "#/definitions/models.ErrorResponse"
                        }
                    },
                    "403": {
                        "description": "Forbidden",
                        "schema": {
                            "$ref": "#/definitions/models.ErrorResponse"
                        }
                    },
                    "404": {
                        "description": "Not Found",
                        "schema": {
                            "$ref": "#/definitions/models.ErrorResponse"
                        }
                    },
                    "500": {
                        "description": "Internal Server Error",
                        "schema": {
                            "$ref": "#/definitions/models.ErrorResponse"
                        }
                    },
                    "default": {
                        "description": "",
                        "schema": {
                            "$ref": "#/definitions/models.ErrorResponse"
                        }
                    }
                }
            }
        },
        "/api/playlists/{id}/tracks": {
            "post": {
                "security": [
                    {
                        "ApiKeyAuth": []
                    }
                ],
                "description": "add new track",
                "consumes": [
                    "application/json"
                ],
                "produces": [
                    "application/json"
                ],
                "tags": [
                    "tracks"
                ],
                "summary": "Add Track",
                "operationId": "add-track",
                "parameters": [
                    {
                        "type": "integer",
                        "description": "playlist id",
                        "name": "id",
                        "in": "path",
                        "required": true
                    },
                    {
                        "description": "track info",
                        "name": "input",
                        "in": "body",
                        "required": true,
                        "schema": {
                            "$ref": "#/definitions/models.AddTrackInput"
                        }
                    }
                ],
                "responses": {
                    "200": {
                        "description": "OK",
                        "schema": {
                            "$ref": "#/definitions/models.CreateResponse"
                        }
                    },
                    "400": {
                        "description": "Bad Request",
                        "schema": {
                            "$ref": "#/definitions/models.ErrorResponse"
                        }
                    },
                    "401": {
                        "description": "Unauthorized",
                        "schema": {
                            "$ref": "#/definitions/models.ErrorResponse"
                        }
                    },
                    "403": {
                        "description": "Forbidden",
                        "schema": {
                            "$ref": "#/definitions/models.ErrorResponse"
                        }
                    },
                    "404": {
                        "description": "Not Found",
                        "schema": {
                            "$ref": "#/definitions/models.ErrorResponse"
                        }
                    },
                    "500": {
                        "description": "Internal Server Error",
                        "schema": {
                            "$ref": "#/definitions/models.ErrorResponse"
                        }
                    },
                    "default": {
                        "description": "",
                        "schema": {
                            "$ref": "#/definitions/models.ErrorResponse"
                        }
                    }
                }
            }
        },
        "/api/playlists/{id}/tracks/{trackID}": {
            "delete": {
                "security": [
                    {
                        "ApiKeyAuth": []
                    }
                ],
                "description": "delete track",
                "produces": [
                    "application/json"
                ],
                "tags": [
                    "tracks"
                ],
                "summary": "Delete Track",
                "operationId": "delete-track",
                "parameters": [
                    {
                        "type": "integer",
                        "description": "playlist id",
                        "name": "id",
                        "in": "path",
                        "required": true
                    },
                    {
                        "type": "integer",
                        "description": "track id",
                        "name": "trackID",
                        "in": "path",
                        "required": true
                    }
                ],
                "responses": {
                    "200": {
                        "description": "OK",
                        "schema": {
                            "$ref": "#/definitions/models.StatusResponse"
                        }
                    },
                    "400": {
                        "description": "Bad Request",
                        "schema": {
                            "$ref": "#/definitions/models.ErrorResponse"
                        }
                    },
                    "401": {
                        "description": "Unauthorized",
                        "schema": {
                            "$ref": "#/definitions/models.ErrorResponse"
                        }
                    },
                    "403": {
                        "description": "Forbidden",
                        "schema": {
                            "$ref": "#/definitions/models.ErrorResponse"
                        }
                    },
                    "404": {
                        "description": "Not Found",
                        "schema": {
                            "$ref": "#/definitions/models.ErrorResponse"
                        }
                    },
                    "500": {
                        "description": "Internal Server Error",
                        "schema": {
                            "$ref": "#/definitions/models.ErrorResponse"
                        }
                    },
                    "default": {
                        "description": "",
                        "schema": {
                            "$ref": "#/definitions/models.ErrorResponse"
                        }
                    }
                }
            }
        },
        "/auth/logout": {
            "post": {
                "description": "logout from service",
                "produces": [
                    "application/json"
                ],
                "tags": [
                    "auth"
                ],
                "summary": "Logout",
                "operationId": "logout",
                "responses": {
                    "200": {
                        "description": "OK",
                        "schema": {
                            "$ref": "#/definitions/models.StatusResponse"
                        }
                    },
                    "400": {
                        "description": "Bad Request",
                        "schema": {
                            "$ref": "#/definitions/models.ErrorResponse"
                        }
                    },
                    "404": {
                        "description": "Not Found",
                        "schema": {
                            "$ref": "#/definitions/models.ErrorResponse"
                        }
                    },
                    "500": {
                        "description": "Internal Server Error",
                        "schema": {
                            "$ref": "#/definitions/models.ErrorResponse"
                        }
                    },
                    "default": {
                        "description": "",
                        "schema": {
                            "$ref": "#/definitions/models.ErrorResponse"
                        }
                    }
                }
            }
        },
        "/refresh-token": {
            "post": {
                "description": "refresh access token",
                "consumes": [
                    "application/json"
                ],
                "produces": [
                    "application/json"
                ],
                "tags": [
                    "auth"
                ],
                "summary": "RefreshToken",
                "operationId": "refresh-token",
                "parameters": [
                    {
                        "description": "user id for token refresh",
                        "name": "input",
                        "in": "body",
                        "required": true,
                        "schema": {
                            "$ref": "#/definitions/models.RefreshTokenInput"
                        }
                    }
                ],
                "responses": {
                    "200": {
                        "description": "OK",
                        "schema": {
                            "type": "object",
                            "additionalProperties": true
                        }
                    },
                    "400": {
                        "description": "Bad Request",
                        "schema": {
                            "$ref": "#/definitions/models.ErrorResponse"
                        }
                    },
                    "404": {
                        "description": "Not Found",
                        "schema": {
                            "$ref": "#/definitions/models.ErrorResponse"
                        }
                    },
                    "500": {
                        "description": "Internal Server Error",
                        "schema": {
                            "$ref": "#/definitions/models.ErrorResponse"
                        }
                    },
                    "default": {
                        "description": "",
                        "schema": {
                            "$ref": "#/definitions/models.ErrorResponse"
                        }
                    }
                }
            }
        }
    },
    "definitions": {
        "models.AddTrackInput": {
            "type": "object",
            "required": [
                "spotifyUri",
                "youTubeMusicID"
            ],
            "properties": {
                "spotifyUri": {
                    "type": "string",
                    "minLength": 1
                },
                "youTubeMusicID": {
                    "type": "string",
                    "minLength": 1
                }
            }
        },
        "models.AllGroupData": {
            "type": "object",
            "properties": {
                "description": {
                    "type": "string"
                },
                "name": {
                    "type": "string"
                },
                "playListID": {
                    "type": "integer"
                },
                "tracks": {
                    "type": "array",
                    "items": {
                        "$ref": "#/definitions/models.Track"
                    }
                },
                "users": {
                    "type": "array",
                    "items": {
                        "$ref": "#/definitions/models.UserGroupData"
                    }
                }
            }
        },
        "models.CreateResponse": {
            "type": "object",
            "properties": {
                "id": {
                    "type": "integer"
                }
            }
        },
        "models.ErrorResponse": {
            "type": "object",
            "properties": {
                "error": {
                    "type": "string"
                }
            }
        },
        "models.Group": {
            "type": "object",
            "required": [
                "description",
                "name"
            ],
            "properties": {
                "description": {
                    "type": "string"
                },
                "id": {
                    "type": "integer"
                },
                "name": {
                    "type": "string"
                }
            }
        },
        "models.PlayList": {
            "type": "object",
            "required": [
                "description",
                "groupID",
                "name"
            ],
            "properties": {
                "description": {
                    "type": "string"
                },
                "groupID": {
                    "type": "integer"
                },
                "id": {
                    "type": "integer"
                },
                "name": {
                    "type": "string"
                }
            }
        },
        "models.RefreshTokenInput": {
            "type": "object",
            "required": [
                "userId"
            ],
            "properties": {
                "userId": {
                    "type": "integer"
                }
            }
        },
        "models.StatusResponse": {
            "type": "object",
            "properties": {
                "status": {
                    "type": "string"
                }
            }
        },
        "models.Track": {
            "type": "object",
            "properties": {
                "id": {
                    "type": "integer"
                },
                "spotifyUri": {
                    "type": "string"
                },
                "youTubeMusicID": {
                    "type": "string"
                }
            }
        },
        "models.UpdateGroupInput": {
            "type": "object",
            "properties": {
                "description": {
                    "type": "string",
                    "maxLength": 50,
                    "minLength": 1
                },
                "name": {
                    "type": "string",
                    "maxLength": 20,
                    "minLength": 1
                }
            }
        },
        "models.UpdatePlayListInput": {
            "type": "object",
            "properties": {
                "description": {
                    "type": "string",
                    "maxLength": 50,
                    "minLength": 1
                },
                "name": {
                    "type": "string",
                    "maxLength": 20,
                    "minLength": 1
                }
            }
        },
        "models.UpdateUserGroupInput": {
            "type": "object",
            "properties": {
                "role": {
                    "type": "string",
                    "maxLength": 20,
                    "minLength": 1
                }
            }
        },
        "models.UserCreateGroupInput": {
            "type": "object",
            "required": [
                "groupDescription",
                "groupName",
                "playListDescription",
                "playListName"
            ],
            "properties": {
                "groupDescription": {
                    "type": "string",
                    "maxLength": 50,
                    "minLength": 1
                },
                "groupName": {
                    "type": "string",
                    "maxLength": 20,
                    "minLength": 1
                },
                "playListDescription": {
                    "type": "string",
                    "maxLength": 50,
                    "minLength": 1
                },
                "playListName": {
                    "type": "string",
                    "maxLength": 20,
                    "minLength": 1
                }
            }
        },
        "models.UserGroupData": {
            "type": "object",
            "properties": {
                "email": {
                    "type": "string"
                },
                "id": {
                    "type": "integer"
                },
                "platform": {
                    "type": "string"
                },
                "roleName": {
                    "type": "string"
                },
                "username": {
                    "type": "string"
                }
            }
        }
    },
    "securityDefinitions": {
        "ApiKeyAuth": {
            "type": "apiKey",
            "name": "Authorization",
            "in": "header"
        }
    }
}